edc_test_utils/__init__.py
edc_test_utils/get_httprequest_for_tests.py
edc_test_utils/get_user_for_tests.py
edc_test_utils/natural_key_test_helper.py
edc_test_utils/webtest.py
edc_test_utils-2.0.0.dist-info/licenses/LICENSE
edc_test_utils-2.0.0.dist-info/WHEEL
edc_test_utils-2.0.0.dist-info/METADATA
edc_test_utils-2.0.0.dist-info/RECORD
